aioretry_decorator
