Metadata-Version: 2.1
Name: aioretry-decorator
Version: 1.0.5
Summary: Handy decorator to set retry policies for async callables with some useful features
Home-page: https://github.com/remort/aioretry
Author: Vadim Bazhov
Author-email: master@remort.net
License: UNKNOWN
Platform: UNKNOWN
Classifier: Intended Audience :: Developers
Classifier: Topic :: Software Development :: Libraries :: Python Modules
Classifier: Programming Language :: Python
Classifier: Programming Language :: Python :: 3
Classifier: Programming Language :: Python :: 3.10
Classifier: Programming Language :: Python :: 3.11
